{
  "approach": {
    "closest_inbound": {
      "approaching_kozr": true,
      "buckets_observed": 7,
      "centroid_lat": 31.2123,
      "centroid_lon": -86.4184,
      "confidence": "moderate",
      "current_distance_nm": 36.51,
      "flash_count": 3166,
      "minutes_to_10nm": null,
      "minutes_to_25nm": null,
      "minutes_to_50nm": null,
      "minutes_to_5nm": null,
      "minutes_to_field": null,
      "motion_bearing_deg": 123,
      "r_squared": 0.537,
      "speed_kts": 13.1
    },
    "tracked_cells": 1
  },
  "closest_strike": {
    "bearing_deg": 136,
    "distance_nm": 1.53,
    "time_iso": "2026-05-07T11:54:00.240330Z"
  },
  "counts": {
    "within_10nm": 23,
    "within_25nm": 128,
    "within_50nm": 318,
    "within_5nm": 12
  },
  "fetched_at": "2026-05-07T11:58:48.911392Z",
  "files_scanned": 90,
  "last_strike": {
    "bearing_deg": 262,
    "distance_nm": 38.22,
    "time_iso": "2026-05-07T11:58:11.610592Z"
  },
  "lookback_min": 10,
  "stagefields": {
    "allen": {
      "closest_strike": {
        "bearing_deg": 308,
        "distance_nm": 2.62,
        "time_iso": "2026-05-07T11:54:00.240330Z"
      },
      "counts": {
        "within_10nm": 18,
        "within_25nm": 116,
        "within_50nm": 315,
        "within_5nm": 8
      },
      "last_strike": {
        "bearing_deg": 266,
        "distance_nm": 41.04,
        "time_iso": "2026-05-07T11:58:11.610592Z"
      }
    },
    "highbluff": {
      "closest_strike": {
        "bearing_deg": 2,
        "distance_nm": 5.29,
        "time_iso": "2026-05-07T11:54:49.205389Z"
      },
      "counts": {
        "within_10nm": 13,
        "within_25nm": 104,
        "within_50nm": 303,
        "within_5nm": 0
      },
      "last_strike": {
        "bearing_deg": 273,
        "distance_nm": 36.69,
        "time_iso": "2026-05-07T11:58:11.610592Z"
      }
    },
    "lucas": {
      "closest_strike": {
        "bearing_deg": 31,
        "distance_nm": 0.61,
        "time_iso": "2026-05-07T11:56:44.658199Z"
      },
      "counts": {
        "within_10nm": 50,
        "within_25nm": 141,
        "within_50nm": 452,
        "within_5nm": 7
      },
      "last_strike": {
        "bearing_deg": 240,
        "distance_nm": 41.75,
        "time_iso": "2026-05-07T11:58:15.453577Z"
      }
    },
    "toth": {
      "closest_strike": {
        "bearing_deg": 339,
        "distance_nm": 4.3,
        "time_iso": "2026-05-07T11:57:09.888230Z"
      },
      "counts": {
        "within_10nm": 13,
        "within_25nm": 122,
        "within_50nm": 314,
        "within_5nm": 1
      },
      "last_strike": {
        "bearing_deg": 267,
        "distance_nm": 45.54,
        "time_iso": "2026-05-07T11:58:11.610592Z"
      }
    }
  },
  "weekend_stations": {
    "K0J4": {
      "closest_strike": {
        "bearing_deg": 5,
        "distance_nm": 8.14,
        "time_iso": "2026-05-07T11:54:35.605404Z"
      },
      "counts": {
        "within_10nm": 11,
        "within_25nm": 166,
        "within_50nm": 463,
        "within_5nm": 0
      },
      "last_strike": {
        "bearing_deg": 274,
        "distance_nm": 49.06,
        "time_iso": "2026-05-07T11:58:17.693983Z"
      }
    },
    "K79J": {
      "closest_strike": {
        "bearing_deg": 185,
        "distance_nm": 3.47,
        "time_iso": "2026-05-07T11:48:57.606627Z"
      },
      "counts": {
        "within_10nm": 67,
        "within_25nm": 131,
        "within_50nm": 538,
        "within_5nm": 5
      },
      "last_strike": {
        "bearing_deg": 255,
        "distance_nm": 46.58,
        "time_iso": "2026-05-07T11:58:17.693983Z"
      }
    },
    "KBCR": {
      "closest_strike": {
        "bearing_deg": 311,
        "distance_nm": 23.69,
        "time_iso": "2026-05-07T11:53:56.633863Z"
      },
      "counts": {
        "within_10nm": 0,
        "within_25nm": 2,
        "within_50nm": 225,
        "within_5nm": 0
      },
      "last_strike": {
        "bearing_deg": 295,
        "distance_nm": 47.94,
        "time_iso": "2026-05-07T11:58:11.610592Z"
      }
    },
    "KDHN": {
      "closest_strike": {
        "bearing_deg": 9,
        "distance_nm": 1.13,
        "time_iso": "2026-05-07T11:50:58.641569Z"
      },
      "counts": {
        "within_10nm": 31,
        "within_25nm": 142,
        "within_50nm": 345,
        "within_5nm": 1
      },
      "last_strike": {
        "bearing_deg": 268,
        "distance_nm": 36.15,
        "time_iso": "2026-05-07T11:58:11.536968Z"
      }
    },
    "KEDN": {
      "closest_strike": {
        "bearing_deg": 181,
        "distance_nm": 0.44,
        "time_iso": "2026-05-07T11:50:46.816970Z"
      },
      "counts": {
        "within_10nm": 35,
        "within_25nm": 158,
        "within_50nm": 369,
        "within_5nm": 4
      },
      "last_strike": {
        "bearing_deg": 242,
        "distance_nm": 48.92,
        "time_iso": "2026-05-07T11:58:15.453577Z"
      }
    },
    "KHEY": {
      "closest_strike": {
        "bearing_deg": 64,
        "distance_nm": 1.03,
        "time_iso": "2026-05-07T11:53:31.996264Z"
      },
      "counts": {
        "within_10nm": 34,
        "within_25nm": 132,
        "within_50nm": 326,
        "within_5nm": 13
      },
      "last_strike": {
        "bearing_deg": 257,
        "distance_nm": 41.83,
        "time_iso": "2026-05-07T11:58:11.610592Z"
      }
    },
    "KLOR": {
      "closest_strike": {
        "bearing_deg": 80,
        "distance_nm": 3.15,
        "time_iso": "2026-05-07T11:49:00.240712Z"
      },
      "counts": {
        "within_10nm": 33,
        "within_25nm": 145,
        "within_50nm": 326,
        "within_5nm": 6
      },
      "last_strike": {
        "bearing_deg": 254,
        "distance_nm": 37.35,
        "time_iso": "2026-05-07T11:58:11.610592Z"
      }
    },
    "KSXS": {
      "closest_strike": {
        "bearing_deg": 218,
        "distance_nm": 1.51,
        "time_iso": "2026-05-07T11:58:06.682309Z"
      },
      "counts": {
        "within_10nm": 39,
        "within_25nm": 167,
        "within_50nm": 324,
        "within_5nm": 7
      },
      "last_strike": {
        "bearing_deg": 251,
        "distance_nm": 32.69,
        "time_iso": "2026-05-07T11:58:11.610592Z"
      }
    }
  }
}